README.txt
bootstrap.py
buildout.cfg
setup.py
Products/__init__.py
Products.MailTemplates.egg-info/PKG-INFO
Products.MailTemplates.egg-info/SOURCES.txt
Products.MailTemplates.egg-info/dependency_links.txt
Products.MailTemplates.egg-info/not-zip-safe
Products.MailTemplates.egg-info/requires.txt
Products.MailTemplates.egg-info/top_level.txt
Products/MailTemplates/BaseMailTemplate.py
Products/MailTemplates/FSMailTemplate.py
Products/MailTemplates/MTMultipart.py
Products/MailTemplates/MailTemplate.py
Products/MailTemplates/__init__.py
Products/MailTemplates/license.txt
Products/MailTemplates/version.txt
Products/MailTemplates/tests/__init__.py
Products/MailTemplates/tests/example1.mt
Products/MailTemplates/tests/example1.py
Products/MailTemplates/tests/example1.txt
Products/MailTemplates/tests/example2.txt
Products/MailTemplates/tests/example3.bin
Products/MailTemplates/tests/example3.mt
Products/MailTemplates/tests/example3.py
Products/MailTemplates/tests/example3.txt
Products/MailTemplates/tests/example4.mt
Products/MailTemplates/tests/example4.py
Products/MailTemplates/tests/example4.txt
Products/MailTemplates/tests/mail_FSSendSimple.txt
Products/MailTemplates/tests/mail_SendAttachment.txt
Products/MailTemplates/tests/mail_SendFile.txt
Products/MailTemplates/tests/mail_SendHeaders.txt
Products/MailTemplates/tests/mail_SendHeaders2.txt
Products/MailTemplates/tests/mail_SendSimple.txt
Products/MailTemplates/tests/mail_SendSimpleSomeHeaders.txt
Products/MailTemplates/tests/mail_unicode.txt
Products/MailTemplates/tests/mail_unicode2.txt
Products/MailTemplates/tests/test.txt
Products/MailTemplates/tests/test_FSMailTemplate.py
Products/MailTemplates/tests/test_MailTemplate.py
Products/MailTemplates/tests/fake_skins/fake_skin/my_mt.mt
Products/MailTemplates/tests/fake_skins/fake_skin/my_mt.mt.metadata
Products/MailTemplates/tests/fake_skins/fake_skin/send_mails.py
Products/MailTemplates/tests/fake_skins/fake_skin/test.mt
Products/MailTemplates/tests/fake_skins/fake_skin/test.mt.metadata
Products/MailTemplates/www/default.txt
Products/MailTemplates/www/fsmt.gif
Products/MailTemplates/www/mt.gif
Products/MailTemplates/www/mtAdd.zpt
Products/MailTemplates/www/mtEdit.zpt
docs/Makefile
docs/changes.txt
docs/conf.py
docs/description.txt
