Metadata-Version: 1.0
Name: Products.MailTemplates
Version: 2.0.0
Summary: MailTemplates for Zope 2
Home-page: http://www.simplistix.co.uk/software/zope/mailtemplates
Author: Chris Withers
Author-email: chris@simplistix.co.uk
License: MIT
Platform: UNKNOWN
Classifier: Development Status :: 5 - Production/Stable
Classifier: Intended Audience :: Developers
Classifier: License :: OSI Approved :: MIT License
